CHANGES.txt
MANIFEST.in
README.txt
buildout.cfg
setup.py
versions.cfg
src/zc/__init__.py
src/zc.wsgisessions.egg-info/PKG-INFO
src/zc.wsgisessions.egg-info/SOURCES.txt
src/zc.wsgisessions.egg-info/dependency_links.txt
src/zc.wsgisessions.egg-info/entry_points.txt
src/zc.wsgisessions.egg-info/namespace_packages.txt
src/zc.wsgisessions.egg-info/not-zip-safe
src/zc.wsgisessions.egg-info/requires.txt
src/zc.wsgisessions.egg-info/top_level.txt
src/zc/wsgisessions/__init__.py
src/zc/wsgisessions/sessions.py
src/zc/wsgisessions/sessions.txt
src/zc/wsgisessions/test.ini
src/zc/wsgisessions/testing.py
src/zc/wsgisessions/tests.py
src/zc/wsgisessions/utils.py
src/zc/wsgisessions/utils.txt
zc.kgs/README.txt
zc.kgs/versions.cfg
zc.kgs/ztk/COPYRIGHT.txt
zc.kgs/ztk/LICENSE.txt
zc.kgs/ztk/README.txt
zc.kgs/ztk/bootstrap.py
zc.kgs/ztk/buildout.cfg
zc.kgs/ztk/development.cfg
zc.kgs/ztk/index.rst
zc.kgs/ztk/zopeapp-versions.cfg
zc.kgs/ztk/zopeapp.cfg
zc.kgs/ztk/ztk-versions.cfg
zc.kgs/ztk/ztk.cfg