Metadata-Version: 1.1
Name: zc.wsgisessions
Version: 0.5.1
Summary: ZC WSGI sessions
Home-page: UNKNOWN
Author: Zope Corporation
Author-email: info@zope.com
License: ZPL 2.1
Keywords: Zope WSGI session
Platform: UNKNOWN
Classifier: Development Status :: 5 - Production/Stable
Classifier: Environment :: Web Environment
Classifier: Framework :: Paste
Classifier: Framework :: Zope3
Classifier: Intended Audience :: Developers
Classifier: Natural Language :: English
Classifier: Operating System :: OS Independent
Classifier: Programming Language :: Python
Classifier: Topic :: Internet :: WWW/HTTP
Classifier: Topic :: Internet :: WWW/HTTP :: WSGI
Classifier: Topic :: Internet :: WWW/HTTP :: WSGI :: Middleware
Classifier: Topic :: Software Development :: Libraries :: Python Modules
